README.rst
setup.py
aiotelebot/__init__.py
aiotelebot/formatters.py
aiotelebot/messages.py
aiotelebot/telegram_api_spec.py
aiotelebot.egg-info/PKG-INFO
aiotelebot.egg-info/SOURCES.txt
aiotelebot.egg-info/dependency_links.txt
aiotelebot.egg-info/requires.txt
aiotelebot.egg-info/top_level.txt
aiotelebot.egg-info/zip-safe