Metadata-Version: 1.1
Name: aiotelebot
Version: 0.2.2
Summary: Service Client Framework powered by Python asyncio.
Home-page: https://github.com/alfred82santa/telebot
Author: alfred82santa
Author-email: alfred82santa@gmail.com
License: UNKNOWN
Platform: UNKNOWN
Classifier: Intended Audience :: Developers
Classifier: Programming Language :: Python
Classifier: Programming Language :: Python :: 3.4
Classifier: Programming Language :: Python :: 3.5
Classifier: License :: OSI Approved :: BSD License
Classifier: Development Status :: 4 - Beta
